README
setup.py
izaber_plpython_zerp/__init__.py
izaber_plpython_zerp/base.py
izaber_plpython_zerp.egg-info/PKG-INFO
izaber_plpython_zerp.egg-info/SOURCES.txt
izaber_plpython_zerp.egg-info/dependency_links.txt
izaber_plpython_zerp.egg-info/not-zip-safe
izaber_plpython_zerp.egg-info/requires.txt
izaber_plpython_zerp.egg-info/top_level.txt