Metadata-Version: 1.1
Name: izaber-plpython-zerp
Version: 1.4
Summary: Base load point for iZaber plpython for Zerp
Home-page: https://github.com/zabertech/izaber-plpython-zerp
Author: Aki Mimoto
Author-email: aki+izaber@zaber.com
License: MIT
Download-URL: https://github.com/zabertech/python-plpython-zerp/archive/1.4.tar.gz
Platform: UNKNOWN
